iclr_downloader/__init__.py
iclr_downloader/core.py
iclr_downloader/commands/download_by_year.py
iclr_downloader-0.1.3.dist-info/METADATA
iclr_downloader-0.1.3.dist-info/WHEEL
iclr_downloader-0.1.3.dist-info/top_level.txt
iclr_downloader-0.1.3.dist-info/RECORD
